mindtrace/jobs/__init__.py
mindtrace/jobs/base/__init__.py
mindtrace/jobs/base/connection_base.py
mindtrace/jobs/base/consumer_base.py
mindtrace/jobs/base/orchestrator_backend.py
mindtrace/jobs/consumers/consumer.py
mindtrace/jobs/core/orchestrator.py
mindtrace/jobs/local/__init__.py
mindtrace/jobs/local/client.py
mindtrace/jobs/local/consumer_backend.py
mindtrace/jobs/local/fifo_queue.py
mindtrace/jobs/local/priority_queue.py
mindtrace/jobs/local/stack.py
mindtrace/jobs/rabbitmq/__init__.py
mindtrace/jobs/rabbitmq/client.py
mindtrace/jobs/rabbitmq/connection.py
mindtrace/jobs/rabbitmq/consumer_backend.py
mindtrace/jobs/redis/__init__.py
mindtrace/jobs/redis/client.py
mindtrace/jobs/redis/connection.py
mindtrace/jobs/redis/consumer_backend.py
mindtrace/jobs/redis/fifo_queue.py
mindtrace/jobs/redis/priority.py
mindtrace/jobs/redis/stack.py
mindtrace/jobs/types/__init__.py
mindtrace/jobs/types/job_specs.py
mindtrace/jobs/utils/__init__.py
mindtrace/jobs/utils/schemas.py
mindtrace_jobs-0.8.0.dist-info/licenses/LICENSE
mindtrace_jobs-0.8.0.dist-info/METADATA
mindtrace_jobs-0.8.0.dist-info/WHEEL
mindtrace_jobs-0.8.0.dist-info/top_level.txt
mindtrace_jobs-0.8.0.dist-info/RECORD
