Metadata-Version: 2.4
Name: mindtrace-jobs
Version: 0.8.0
Summary: Job management for Mindtrace
Author: Mindtrace Team
License-Expression: Apache-2.0
Project-URL: Homepage, https://mindtrace.ai
Project-URL: Repository, https://github.com/mindtrace/mindtrace/blob/main/mindtrace/jobs
Classifier: Programming Language :: Python :: 3
Classifier: Programming Language :: Python :: 3.12
License-File: LICENSE
Requires-Dist: mindtrace-core>=0.8.0
Requires-Dist: mindtrace-registry>=0.8.0
Requires-Dist: pika>=1.3.2
Requires-Dist: pydantic>=2.11.1
Requires-Dist: redis>=5.3.0
Dynamic: license-file
